dephash.py
dephash-1.0.0.dist-info/METADATA
dephash-1.0.0.dist-info/RECORD
dephash-1.0.0.dist-info/WHEEL
dephash-1.0.0.dist-info/entry_points.txt
dephash-1.0.0.dist-info/top_level.txt
