Metadata-Version: 2.1
Name: dephash
Version: 1.0.0
Summary: requirements.txt dependency hasher
Home-page: https://github.com/escapewindow/dephash
Author: Aki Sasaki
Author-email: aki@escapewindow.com
License: MPL2
Platform: UNKNOWN
Classifier: Intended Audience :: Developers
Classifier: Natural Language :: English
Classifier: Programming Language :: Python :: 2.7
Classifier: Programming Language :: Python :: 3.5
Classifier: Programming Language :: Python :: 3.6
Requires-Dist: click
Requires-Dist: hashin (>=0.7.1)
Requires-Dist: pip (>=8.1.2)
Requires-Dist: six
Requires-Dist: virtualenv
